bitpin/__init__.py
bitpin/_utils.py
bitpin/clients/__init__.py
bitpin/clients/async_client.py
bitpin/clients/client.py
bitpin/clients/core.py
bitpin/enums.py
bitpin/exceptions.py
bitpin/types.py
python_bitpin-0.0.11.dist-info/LICENSE
python_bitpin-0.0.11.dist-info/METADATA
python_bitpin-0.0.11.dist-info/WHEEL
python_bitpin-0.0.11.dist-info/RECORD
