Metadata-Version: 2.1
Name: python-bitpin
Version: 0.0.11
Summary: Bitpin Exchange Python SDK
License: MIT
Author: AMiWR
Author-email: amiwrpremium@gmail.com
Requires-Python: >=3.9,<4.0
Classifier: License :: OSI Approved :: MIT License
Classifier: Programming Language :: Python :: 3
Classifier: Programming Language :: Python :: 3.9
Classifier: Programming Language :: Python :: 3.10
Classifier: Programming Language :: Python :: 3.11
Classifier: Programming Language :: Python :: 3.12
Requires-Dist: aiohttp (>=3.8.5,<4.0.0)
Requires-Dist: pysocks (>=1.7.1,<2.0.0)
Requires-Dist: requests (>=2.31.0,<3.0.0)
